Metadata-Version: 2.1
Name: intraloxsensing-python-client
Version: 0.0.1
Summary: This package is used in python to ease the process of configuring datasets and uploading data to the Intralox Sensing Portal.
Author: Jason Daming
